capek/__init__.py
capek/client.py
capek/control.py
capek/driver.py
capek/protocol.py
capek/state.py
capek-0.1.0.dist-info/LICENSE
capek-0.1.0.dist-info/METADATA
capek-0.1.0.dist-info/WHEEL
capek-0.1.0.dist-info/top_level.txt
capek-0.1.0.dist-info/RECORD
