Metadata-Version: 2.1
Name: capek
Version: 0.1.0
Summary: Python library for developing TORCS racing robots
Home-page: https://github.com/dikuchan/capek
Author: dikuchan
Author-email: dikuchan@protonmail.com
License: UNKNOWN
Platform: UNKNOWN
Classifier: Programming Language :: Python :: 3
Classifier: License :: OSI Approved :: MIT License
Classifier: Development Status :: 5 - Production/Stable
Classifier: Operating System :: POSIX :: Linux
Classifier: Topic :: Scientific/Engineering :: Artificial Intelligence
Requires-Python: >=3.7
License-File: LICENSE
